plugin_manager/__init__.py
plugin_manager/exceptions.py
plugin_manager/manager.py
plugin_manager/plugin.py
simple_plugin_manager_zimolab1995-0.0.5.dist-info/LICENSE
simple_plugin_manager_zimolab1995-0.0.5.dist-info/METADATA
simple_plugin_manager_zimolab1995-0.0.5.dist-info/WHEEL
simple_plugin_manager_zimolab1995-0.0.5.dist-info/top_level.txt
simple_plugin_manager_zimolab1995-0.0.5.dist-info/RECORD
