Metadata-Version: 2.1
Name: simple-plugin-manager-zimolab1995
Version: 0.0.5
Summary: A simple plugin manager for python project
Author-email: zimolab1995 <zimolab@aliyun.com>
Project-URL: Homepage, https://gitee.com/zimolab1995/simple_plugin_manager
Project-URL: Bug Tracker, https://gitee.com/zimolab1995/simple_plugin_manager/issues
Classifier: Programming Language :: Python :: 3
Classifier: License :: OSI Approved :: MIT License
Classifier: Operating System :: OS Independent
Requires-Python: >=3.7
License-File: LICENSE
Requires-Dist: code-exec (>=0.0.2)
Requires-Dist: dulwich (>=0.21.5)
